{"is_source_file": false, "format": "", "description": "", "external_files": [], "external_methods": [], "published": [], "classes": [], "methods": [], "calls": [], "search-terms": ["recipe-hub-36504-36545"], "state": 2, "file_id": 1, "knowledge_revision": 6, "git_revision": "7ed7403b9c293be7cb5167c175499383d7e330c1", "hash": "eb2b2e7d39fefefbd13a0c8aeaf55fe9", "format-version": 4, "code-base-name": "recipe_backend", "filename": "README.md", "revision_history": [{"6": "7ed7403b9c293be7cb5167c175499383d7e330c1"}]}